LICENSE.txt
MANIFEST.in
README.rst
setup.py
pidigits/__init__.py
pidigits/pidigits.py
pidigits/pidigits_gosper.py
pidigits/pidigits_lambert.py
pidigits/taudigits.py
pidigits/taudigits_lambert.py
pidigits.egg-info/PKG-INFO
pidigits.egg-info/SOURCES.txt
pidigits.egg-info/dependency_links.txt
pidigits.egg-info/not-zip-safe
pidigits.egg-info/top_level.txt