Metadata-Version: 1.1
Name: pidigits
Version: 0.5
Summary: Generate arbitrary number of digits of Pi  or Tau using a streaming algorithm.
Home-page: https://github.com/transmogrifier/pidigits
Author: Sameer Marathe
Author-email: transmogrifier@gmail.com
License: Apache License 2.0
Keywords: mathematics number_theory pi spigot_algorithm
Platform: UNKNOWN
Classifier: Development Status :: 5 - Production/Stable
Classifier: License :: OSI Approved :: Apache Software License
Classifier: Programming Language :: Python :: 2.7
Classifier: Programming Language :: Python :: 3.4
Classifier: Topic :: Scientific/Engineering :: Mathematics
Classifier: Intended Audience :: Developers
Classifier: Intended Audience :: Science/Research
Classifier: Intended Audience :: End Users/Desktop
